fastestimator/__init__.py
fastestimator/estimator.py
fastestimator/network.py
fastestimator/pipeline.py
fastestimator/architecture/__init__.py
fastestimator/architecture/pytorch/__init__.py
fastestimator/architecture/pytorch/attention_unet.py
fastestimator/architecture/pytorch/lenet.py
fastestimator/architecture/pytorch/resnet9.py
fastestimator/architecture/pytorch/unet.py
fastestimator/architecture/pytorch/wideresnet.py
fastestimator/architecture/tensorflow/__init__.py
fastestimator/architecture/tensorflow/attention_unet.py
fastestimator/architecture/tensorflow/lenet.py
fastestimator/architecture/tensorflow/resnet9.py
fastestimator/architecture/tensorflow/unet.py
fastestimator/architecture/tensorflow/wideresnet.py
fastestimator/backend/__init__.py
fastestimator/backend/_abs.py
fastestimator/backend/_argmax.py
fastestimator/backend/_binary_crossentropy.py
fastestimator/backend/_cast.py
fastestimator/backend/_categorical_crossentropy.py
fastestimator/backend/_check_nan.py
fastestimator/backend/_clip_by_value.py
fastestimator/backend/_concat.py
fastestimator/backend/_convert_tensor_precision.py
fastestimator/backend/_dice_score.py
fastestimator/backend/_exp.py
fastestimator/backend/_expand_dims.py
fastestimator/backend/_feed_forward.py
fastestimator/backend/_flip.py
fastestimator/backend/_focal_loss.py
fastestimator/backend/_gather.py
fastestimator/backend/_gather_from_batch.py
fastestimator/backend/_get_gradient.py
fastestimator/backend/_get_image_dims.py
fastestimator/backend/_get_lr.py
fastestimator/backend/_get_shape.py
fastestimator/backend/_hinge.py
fastestimator/backend/_huber.py
fastestimator/backend/_iwd.py
fastestimator/backend/_l1_loss.py
fastestimator/backend/_l2_regularization.py
fastestimator/backend/_lambertw.py
fastestimator/backend/_load_model.py
fastestimator/backend/_matmul.py
fastestimator/backend/_maximum.py
fastestimator/backend/_mean_squared_error.py
fastestimator/backend/_ones_like.py
fastestimator/backend/_percentile.py
fastestimator-1.7.0.dist-info/LICENSE
fastestimator-1.7.0.dist-info/METADATA
fastestimator-1.7.0.dist-info/WHEEL
fastestimator-1.7.0.dist-info/entry_points.txt
fastestimator-1.7.0.dist-info/top_level.txt
fastestimator-1.7.0.dist-info/RECORD
