Metadata-Version: 2.1
Name: fastestimator
Version: 1.7.0
Summary: Deep learning framework
Home-page: https://github.com/fastestimator/fastestimator
Author: FastEstimator Dev
License: Apache License 2.0
Keywords: fastestimator tensorflow pytorch
Classifier: License :: OSI Approved :: Apache Software License
Classifier: Programming Language :: Python :: 3
Requires-Python: >=3.10.0
License-File: LICENSE
Requires-Dist: albumentations==1.4.1
Requires-Dist: matplotlib==3.9.2
Requires-Dist: h5py==3.11.0
Requires-Dist: scipy
Requires-Dist: PyLaTeX==1.4.1
Requires-Dist: natsort==8.3.1
Requires-Dist: tensorflow-probability==0.22.1
Requires-Dist: transformers==4.38.2
Requires-Dist: torchinfo==1.7.2
Requires-Dist: graphviz==0.20.1
Requires-Dist: torchview==0.2.6
Requires-Dist: pydot==1.4.2
Requires-Dist: dot2tex==2.11.3
Requires-Dist: gdown==4.6.4
Requires-Dist: PySocks==1.7.1
Requires-Dist: uncertainty-calibration==0.1.4
Requires-Dist: dill==0.3.6
Requires-Dist: scikit-image==0.21.0
Requires-Dist: prettytable==3.6.0
Requires-Dist: nltk==3.8.1
Requires-Dist: requests==2.32.2
Requires-Dist: tqdm==4.66.5
Requires-Dist: numpy==1.26.4
Requires-Dist: pyfiglet==0.8.post1
Requires-Dist: opencv-python==4.7.0.72
Requires-Dist: pandas==2.0.1
Requires-Dist: wget==3.2
Requires-Dist: pillow==10.4.0
Requires-Dist: jsonpickle==3.0.1
Requires-Dist: python-docx==0.8.11
Requires-Dist: plotly==5.13.1
Requires-Dist: kaleido==0.2.1
Requires-Dist: orjson==3.8.7
Requires-Dist: scikit-learn==1.3.2
Requires-Dist: lazy-loader==0.2
Requires-Dist: fe-pycocotools==1.0
Requires-Dist: typing-extensions==4.12.2
Requires-Dist: charset-normalizer==3.3.2
Requires-Dist: py-cpuinfo==9.0.0
Requires-Dist: fastparquet==2024.2.0
Requires-Dist: jax==0.4.33
Requires-Dist: jaxlib==0.4.33
